iidfile/__init__.py
iidfile/iidfile.py
tests/__init__.py
tests/default.py
tests/graphs.py
tests/sketch.py
iidfile-0.2.0.dist-info/LICENSE
iidfile-0.2.0.dist-info/METADATA
iidfile-0.2.0.dist-info/WHEEL
iidfile-0.2.0.dist-info/top_level.txt
iidfile-0.2.0.dist-info/RECORD
