Metadata-Version: 2.1
Name: iidfile
Version: 0.2.0
Summary: File parser for .iid files, for storing labeled image segmentation data.
Home-page: https://github.com/aeaeaeaeaeae/iidformat
Author: aeaeaeae
Author-email: ouououou@aeaeaeae.io
License: UNKNOWN
Platform: UNKNOWN
Classifier: Programming Language :: Python :: 3
Classifier: License :: OSI Approved :: GNU Lesser General Public License v3 (LGPLv3)
Classifier: Operating System :: OS Independent
Classifier: Development Status :: 4 - Beta
Requires-Python: >=3.6
